{
"bones": [
	{ "name": "root" },
	{ "name": "Body", "parent": "root", "length": 17.31, "x": 10, "y": 10.92, "rotation": 157.34 },
	{ "name": "BackLeftLeg", "parent": "Body", "length": 11.11, "x": 1.57, "y": -1.26, "rotation": 122.52 },
	{ "name": "BackRightLeg", "parent": "Body", "length": 12.57, "x": 4.58, "y": -0.53, "rotation": 98.94 },
	{ "name": "Chest", "parent": "Body", "length": 10.14, "x": 19.77, "y": -0.99, "rotation": 111.48 },
	{ "name": "FrontLeftLeg", "parent": "Body", "length": 13.2, "x": 11.31, "y": 0.88, "rotation": 111.09 },
	{ "name": "FrontRightLeg", "parent": "Body", "length": 11.38, "x": 18.25, "y": 5.17, "rotation": 104.14 },
	{ "name": "Tail", "parent": "Body", "length": 11.85, "x": 0.64, "y": -3.21, "rotation": -108.7 },
	{ "name": "head", "parent": "Body", "length": 14.32, "x": 17.89, "y": -5.26, "rotation": -67.73 }
],
"slots": [
	{ "name": "BackLeg_012", "bone": "BackRightLeg", "attachment": "BackLeg/BackLeg_01" },
	{ "name": "FrontRightLeg", "bone": "FrontRightLeg", "attachment": "FrontRightLeg" },
	{ "name": "Body_01", "bone": "Body", "attachment": "Body/Body_01" },
	{ "name": "Tail", "bone": "Tail", "attachment": "Tail" },
	{ "name": "Chest", "bone": "Chest", "attachment": "Chest" },
	{ "name": "BackLeg_01", "bone": "BackLeftLeg", "attachment": "BackLeg/BackLeg_01" },
	{ "name": "FrontLeftLeg", "bone": "FrontLeftLeg", "attachment": "FrontLeftLeg" },
	{ "name": "Head_01", "bone": "head", "attachment": "Head/Head_01" }
],
"skins": {
	"default": {
		"BackLeg_01": {
			"BackLeg/BackLeg_01": { "x": 6.23, "y": -0.09, "rotation": 80.12, "width": 12, "height": 14 }
		},
		"BackLeg_012": {
			"BackLeg/BackLeg_01": { "x": 7.11, "y": -1.37, "rotation": 103.7, "width": 12, "height": 14 }
		},
		"Body_01": {
			"Body/Body_01": { "x": 3.43, "y": -0.38, "rotation": -157.34, "width": 18, "height": 20 }
		},
		"Chest": {
			"Chest": { "x": 5.37, "y": 1.45, "rotation": 91.16, "width": 17, "height": 19 }
		},
		"FrontLeftLeg": {
			"FrontLeftLeg": { "x": 7.88, "rotation": 91.55, "width": 10, "height": 16 }
		},
		"FrontRightLeg": {
			"FrontRightLeg": { "x": 8.18, "y": 0.02, "rotation": 98.5, "width": 10, "height": 11 }
		},
		"Head_01": {
			"Head/Head_01": { "x": 10.36, "y": 1.09, "rotation": -89.61, "width": 25, "height": 23 }
		},
		"Tail": {
			"Tail": { "x": 7.75, "y": -3.61, "rotation": -48.64, "width": 19, "height": 18 }
		}
	}
},
"animations": {
	"dead": {
		"bones": {
			"root": {
				"rotate": [
					{ "time": 0, "angle": 0 }
				],
				"translate": [
					{ "time": 0, "x": 0, "y": 0 }
				],
				"scale": [
					{ "time": 0, "x": 1, "y": 1 }
				]
			},
			"Body": {
				"rotate": [
					{ "time": 0, "angle": 0 },
					{ "time": 0.3333, "angle": 21.74 }
				],
				"translate": [
					{ "time": 0, "x": 0, "y": 0 },
					{ "time": 0.3333, "x": 0, "y": -4.05 }
				],
				"scale": [
					{ "time": 0, "x": 1, "y": 1 }
				]
			},
			"BackLeftLeg": {
				"rotate": [
					{ "time": 0, "angle": 0 },
					{ "time": 0.3333, "angle": 50.41 }
				],
				"translate": [
					{ "time": 0, "x": 0, "y": 0 },
					{ "time": 0.3333, "x": 3.68, "y": 4.42 }
				],
				"scale": [
					{ "time": 0, "x": 1, "y": 1 }
				]
			},
			"BackRightLeg": {
				"rotate": [
					{ "time": 0, "angle": 0 },
					{ "time": 0.3333, "angle": 64.03 }
				],
				"translate": [
					{ "time": 0, "x": 0, "y": 0 },
					{ "time": 0.3333, "x": 3.14, "y": -0.15 }
				],
				"scale": [
					{ "time": 0, "x": 1, "y": 1 }
				]
			},
			"Chest": {
				"rotate": [
					{ "time": 0, "angle": 0 },
					{ "time": 0.3333, "angle": 36.17 }
				],
				"translate": [
					{ "time": 0, "x": 0, "y": 0 }
				],
				"scale": [
					{ "time": 0, "x": 1, "y": 1 }
				]
			},
			"FrontLeftLeg": {
				"rotate": [
					{ "time": 0, "angle": 0 },
					{ "time": 0.3333, "angle": -92.86 }
				],
				"translate": [
					{ "time": 0, "x": 0, "y": 0 }
				],
				"scale": [
					{ "time": 0, "x": 1, "y": 1 }
				]
			},
			"FrontRightLeg": {
				"rotate": [
					{ "time": 0, "angle": 0 },
					{ "time": 0.3333, "angle": -94.02 }
				],
				"translate": [
					{ "time": 0, "x": 0, "y": 0 },
					{ "time": 0.3333, "x": -1.28, "y": -1.84 }
				],
				"scale": [
					{ "time": 0, "x": 1, "y": 1, "curve": "stepped" },
					{ "time": 0.3333, "x": 1, "y": 1 }
				]
			},
			"Tail": {
				"rotate": [
					{ "time": 0, "angle": 0 },
					{ "time": 0.3333, "angle": -48.79 }
				],
				"translate": [
					{ "time": 0, "x": 0, "y": 0 }
				],
				"scale": [
					{ "time": 0, "x": 1, "y": 1 }
				]
			},
			"head": {
				"rotate": [
					{ "time": 0, "angle": 0 },
					{ "time": 0.3333, "angle": 6.97 }
				],
				"translate": [
					{ "time": 0, "x": 0, "y": 0 },
					{ "time": 0.3333, "x": -0.01, "y": 0.91 }
				],
				"scale": [
					{ "time": 0, "x": 1, "y": 1 }
				]
			}
		},
		"slots": {
			"BackLeg_01": {
				"color": [
					{ "time": 0, "color": "ffffffff" },
					{ "time": 0.3333, "color": "647dc8ff" }
				]
			},
			"BackLeg_012": {
				"color": [
					{ "time": 0, "color": "ffffffff" },
					{ "time": 0.3333, "color": "647dc8ff" }
				]
			},
			"Body_01": {
				"color": [
					{ "time": 0, "color": "ffffffff" },
					{ "time": 0.3333, "color": "647dc8ff" }
				]
			},
			"Chest": {
				"color": [
					{ "time": 0, "color": "ffffffff" },
					{ "time": 0.3333, "color": "647dc8ff" }
				]
			},
			"FrontLeftLeg": {
				"color": [
					{ "time": 0, "color": "ffffffff" },
					{ "time": 0.3333, "color": "647dc8ff" }
				]
			},
			"FrontRightLeg": {
				"color": [
					{ "time": 0, "color": "ffffffff" },
					{ "time": 0.3333, "color": "647dc8ff" }
				]
			},
			"Head_01": {
				"color": [
					{ "time": 0, "color": "ffffffff" },
					{ "time": 0.3333, "color": "647dc8ff" }
				]
			},
			"Tail": {
				"color": [
					{ "time": 0, "color": "ffffffff" },
					{ "time": 0.3333, "color": "647dc8ff" }
				]
			}
		}
	},
	"idle": {
		"bones": {
			"root": {
				"rotate": [
					{ "time": 0, "angle": 0, "curve": "stepped" },
					{ "time": 1.8, "angle": 0 }
				],
				"translate": [
					{ "time": 0, "x": 0, "y": 0, "curve": "stepped" },
					{ "time": 1.8, "x": 0, "y": 0 }
				],
				"scale": [
					{ "time": 0, "x": 1, "y": 1, "curve": "stepped" },
					{ "time": 1.8, "x": 1, "y": 1 }
				]
			},
			"Body": {
				"rotate": [
					{ "time": 0, "angle": 0, "curve": "stepped" },
					{ "time": 1.8, "angle": 0 }
				],
				"translate": [
					{ "time": 0, "x": 0, "y": 0, "curve": "stepped" },
					{ "time": 1.8, "x": 0, "y": 0 }
				],
				"scale": [
					{ "time": 0, "x": 1, "y": 1 },
					{ "time": 0.9, "x": 1.05, "y": 1 },
					{ "time": 1.8, "x": 1, "y": 1 }
				]
			},
			"BackLeftLeg": {
				"rotate": [
					{ "time": 0, "angle": 0, "curve": "stepped" },
					{ "time": 1.8, "angle": 0 }
				],
				"translate": [
					{ "time": 0, "x": 0, "y": 0, "curve": "stepped" },
					{ "time": 1.8, "x": 0, "y": 0 }
				],
				"scale": [
					{ "time": 0, "x": 1, "y": 1, "curve": "stepped" },
					{ "time": 1.8, "x": 1, "y": 1 }
				]
			},
			"BackRightLeg": {
				"rotate": [
					{ "time": 0, "angle": 0, "curve": "stepped" },
					{ "time": 1.8, "angle": 0 }
				],
				"translate": [
					{ "time": 0, "x": 0, "y": 0, "curve": "stepped" },
					{ "time": 1.8, "x": 0, "y": 0 }
				],
				"scale": [
					{ "time": 0, "x": 1, "y": 1, "curve": "stepped" },
					{ "time": 1.8, "x": 1, "y": 1 }
				]
			},
			"Chest": {
				"rotate": [
					{ "time": 0, "angle": 0, "curve": "stepped" },
					{ "time": 1.8, "angle": 0 }
				],
				"translate": [
					{ "time": 0, "x": 0, "y": 0, "curve": "stepped" },
					{ "time": 1.8, "x": 0, "y": 0 }
				],
				"scale": [
					{ "time": 0, "x": 1, "y": 1, "curve": "stepped" },
					{ "time": 1.8, "x": 1, "y": 1 }
				]
			},
			"FrontLeftLeg": {
				"rotate": [
					{ "time": 0, "angle": 0, "curve": "stepped" },
					{ "time": 1.8, "angle": 0 }
				],
				"translate": [
					{ "time": 0, "x": 0, "y": 0, "curve": "stepped" },
					{ "time": 1.8, "x": 0, "y": 0 }
				],
				"scale": [
					{ "time": 0, "x": 1, "y": 1, "curve": "stepped" },
					{ "time": 1.8, "x": 1, "y": 1 }
				]
			},
			"FrontRightLeg": {
				"rotate": [
					{ "time": 0, "angle": 0, "curve": "stepped" },
					{ "time": 1.8, "angle": 0 }
				],
				"translate": [
					{ "time": 0, "x": 0, "y": 0, "curve": "stepped" },
					{ "time": 1.8, "x": 0, "y": 0 }
				],
				"scale": [
					{ "time": 0, "x": 1, "y": 1, "curve": "stepped" },
					{ "time": 1.8, "x": 1, "y": 1 }
				]
			},
			"Tail": {
				"rotate": [
					{ "time": 0, "angle": 0, "curve": "stepped" },
					{ "time": 1.8, "angle": 0 }
				],
				"translate": [
					{ "time": 0, "x": 0, "y": 0, "curve": "stepped" },
					{ "time": 1.8, "x": 0, "y": 0 }
				],
				"scale": [
					{ "time": 0, "x": 1, "y": 1, "curve": "stepped" },
					{ "time": 1.8, "x": 1, "y": 1 }
				]
			},
			"head": {
				"rotate": [
					{ "time": 0, "angle": 0, "curve": "stepped" },
					{ "time": 1.8, "angle": 0 }
				],
				"translate": [
					{ "time": 0, "x": 0, "y": 0, "curve": "stepped" },
					{ "time": 1.8, "x": 0, "y": 0 }
				],
				"scale": [
					{ "time": 0, "x": 1, "y": 1, "curve": "stepped" },
					{ "time": 1.8, "x": 1, "y": 1 }
				]
			}
		}
	},
	"jump": {
		"bones": {
			"root": {
				"rotate": [
					{ "time": 0, "angle": 0 }
				],
				"translate": [
					{ "time": 0, "x": 0, "y": 0 }
				],
				"scale": [
					{ "time": 0, "x": 1, "y": 1 }
				]
			},
			"Body": {
				"rotate": [
					{ "time": 0, "angle": 0 },
					{ "time": 0.1666, "angle": -13.8 }
				],
				"translate": [
					{ "time": 0, "x": 0, "y": 0 }
				],
				"scale": [
					{ "time": 0, "x": 1, "y": 1 }
				]
			},
			"BackLeftLeg": {
				"rotate": [
					{ "time": 0, "angle": 0 },
					{ "time": 0.1666, "angle": 39.93 }
				],
				"translate": [
					{ "time": 0, "x": 0, "y": 0 },
					{ "time": 0.1666, "x": 2.62, "y": 3.45 }
				],
				"scale": [
					{ "time": 0, "x": 1, "y": 1 }
				]
			},
			"BackRightLeg": {
				"rotate": [
					{ "time": 0, "angle": 0 },
					{ "time": 0.1666, "angle": 28.01 }
				],
				"translate": [
					{ "time": 0, "x": 0, "y": 0 },
					{ "time": 0.1666, "x": 1.14, "y": -1.54 }
				],
				"scale": [
					{ "time": 0, "x": 1, "y": 1 }
				]
			},
			"Chest": {
				"rotate": [
					{ "time": 0, "angle": 0 },
					{ "time": 0.1666, "angle": 23.18 }
				],
				"translate": [
					{ "time": 0, "x": 0, "y": 0 },
					{ "time": 0.1666, "x": -1.96, "y": 0.94 }
				],
				"scale": [
					{ "time": 0, "x": 1, "y": 1 }
				]
			},
			"FrontLeftLeg": {
				"rotate": [
					{ "time": 0, "angle": 0 },
					{ "time": 0.1666, "angle": -67.89 }
				],
				"translate": [
					{ "time": 0, "x": 0, "y": 0 },
					{ "time": 0.1666, "x": -2.63, "y": -2.57 }
				],
				"scale": [
					{ "time": 0, "x": 1, "y": 1 }
				]
			},
			"FrontRightLeg": {
				"rotate": [
					{ "time": 0, "angle": 0 },
					{ "time": 0.1666, "angle": -70.67 }
				],
				"translate": [
					{ "time": 0, "x": 0, "y": 0 },
					{ "time": 0.1666, "x": -3.26, "y": -2.41 }
				],
				"scale": [
					{ "time": 0, "x": 1, "y": 1 }
				]
			},
			"Tail": {
				"rotate": [
					{ "time": 0, "angle": 0 },
					{ "time": 0.1666, "angle": -27.67 }
				],
				"translate": [
					{ "time": 0, "x": 0, "y": 0 },
					{ "time": 0.1666, "x": 0.89, "y": 0.66 }
				],
				"scale": [
					{ "time": 0, "x": 1, "y": 1 }
				]
			},
			"head": {
				"rotate": [
					{ "time": 0, "angle": 0 },
					{ "time": 0.1666, "angle": 15.3 }
				],
				"translate": [
					{ "time": 0, "x": 0, "y": 0 },
					{ "time": 0.1666, "x": -1.02, "y": 1.38 }
				],
				"scale": [
					{ "time": 0, "x": 1, "y": 1 }
				]
			}
		}
	},
	"walk": {
		"bones": {
			"root": {
				"rotate": [
					{ "time": 0, "angle": 0, "curve": "stepped" },
					{ "time": 0.6666, "angle": 0 }
				],
				"translate": [
					{ "time": 0, "x": 0, "y": 0, "curve": "stepped" },
					{ "time": 0.6666, "x": 0, "y": 0 }
				],
				"scale": [
					{ "time": 0, "x": 1, "y": 1, "curve": "stepped" },
					{ "time": 0.6666, "x": 1, "y": 1 }
				]
			},
			"Body": {
				"rotate": [
					{ "time": 0, "angle": 0 },
					{ "time": 0.1666, "angle": 18.66 },
					{ "time": 0.5, "angle": 12.33 },
					{ "time": 0.6666, "angle": 0 }
				],
				"translate": [
					{ "time": 0, "x": 0, "y": 0 },
					{ "time": 0.5, "x": -0.1, "y": 1.31 },
					{ "time": 0.6666, "x": 0, "y": 0 }
				],
				"scale": [
					{ "time": 0, "x": 1, "y": 1, "curve": "stepped" },
					{ "time": 0.6666, "x": 1, "y": 1 }
				]
			},
			"BackLeftLeg": {
				"rotate": [
					{ "time": 0, "angle": -22.62 },
					{ "time": 0.1666, "angle": -18.84 },
					{ "time": 0.3333, "angle": 48.4 },
					{ "time": 0.5, "angle": -35.75 },
					{ "time": 0.6666, "angle": -22.62 }
				],
				"translate": [
					{ "time": 0, "x": 0, "y": 0 },
					{ "time": 0.3333, "x": 0.97, "y": 2.54 },
					{ "time": 0.5, "x": -0.97, "y": -0.89 },
					{ "time": 0.6666, "x": 0, "y": 0 }
				],
				"scale": [
					{ "time": 0, "x": 1, "y": 1, "curve": "stepped" },
					{ "time": 0.6666, "x": 1, "y": 1 }
				]
			},
			"BackRightLeg": {
				"rotate": [
					{ "time": 0, "angle": -13.75 },
					{ "time": 0.1666, "angle": -18.9 },
					{ "time": 0.3333, "angle": 71.94 },
					{ "time": 0.5, "angle": -38.18 },
					{ "time": 0.6666, "angle": -13.75 }
				],
				"translate": [
					{ "time": 0, "x": 0, "y": 0, "curve": "stepped" },
					{ "time": 0.6666, "x": 0, "y": 0 }
				],
				"scale": [
					{ "time": 0, "x": 1, "y": 1, "curve": "stepped" },
					{ "time": 0.6666, "x": 1, "y": 1 }
				]
			},
			"Chest": {
				"rotate": [
					{ "time": 0, "angle": 1.71 },
					{ "time": 0.1666, "angle": 17.58 },
					{ "time": 0.3333, "angle": 22.24 },
					{ "time": 0.5, "angle": 8.4 },
					{ "time": 0.6666, "angle": 1.71 }
				],
				"translate": [
					{ "time": 0, "x": 0, "y": 0 },
					{ "time": 0.1666, "x": -0.5, "y": 0.47 },
					{ "time": 0.3333, "x": -2.06, "y": -0.12 },
					{ "time": 0.5, "x": -1.47, "y": -0.2 },
					{ "time": 0.6666, "x": 0, "y": 0 }
				],
				"scale": [
					{ "time": 0, "x": 1, "y": 1, "curve": "stepped" },
					{ "time": 0.6666, "x": 1, "y": 1 }
				]
			},
			"FrontLeftLeg": {
				"rotate": [
					{ "time": 0, "angle": 1.78 },
					{ "time": 0.1666, "angle": -74.81 },
					{ "time": 0.3333, "angle": -87.57 },
					{ "time": 0.5, "angle": -11.04 },
					{ "time": 0.6666, "angle": 1.78 }
				],
				"translate": [
					{ "time": 0, "x": 0, "y": 0, "curve": "stepped" },
					{ "time": 0.6666, "x": 0, "y": 0 }
				],
				"scale": [
					{ "time": 0, "x": 1, "y": 1, "curve": "stepped" },
					{ "time": 0.6666, "x": 1, "y": 1 }
				]
			},
			"FrontRightLeg": {
				"rotate": [
					{ "time": 0, "angle": 3.08 },
					{ "time": 0.1666, "angle": -70.91 },
					{ "time": 0.3333, "angle": -88.4 },
					{ "time": 0.5, "angle": -13.28 },
					{ "time": 0.6666, "angle": 3.08 }
				],
				"translate": [
					{ "time": 0, "x": 0, "y": 0 },
					{ "time": 0.0333, "x": -0.68, "y": -1.16 },
					{ "time": 0.3333, "x": -3.1, "y": -3.87 },
					{ "time": 0.3666, "x": -3.03, "y": -4.27 },
					{ "time": 0.4, "x": -3.22, "y": -4.61 },
					{ "time": 0.4666, "x": -2.03, "y": -4.42 },
					{ "time": 0.5, "x": -0.87, "y": -3.14 },
					{ "time": 0.6, "x": -0.51, "y": -1.73 },
					{ "time": 0.6333, "x": -0.5, "y": -1.06 },
					{ "time": 0.6666, "x": -0.05, "y": -0.13 }
				],
				"scale": [
					{ "time": 0, "x": 1, "y": 1, "curve": "stepped" },
					{ "time": 0.6666, "x": 1, "y": 1 }
				]
			},
			"Tail": {
				"rotate": [
					{ "time": 0, "angle": -7.91 },
					{ "time": 0.1666, "angle": 0.77 },
					{ "time": 0.3333, "angle": 11.77 },
					{ "time": 0.5, "angle": -3.12 },
					{ "time": 0.6666, "angle": -7.91 }
				],
				"translate": [
					{ "time": 0, "x": 0, "y": 0 },
					{ "time": 0.3333, "x": -0.1, "y": 0.59 },
					{ "time": 0.6666, "x": 0, "y": 0 }
				],
				"scale": [
					{ "time": 0, "x": 1, "y": 1, "curve": "stepped" },
					{ "time": 0.6666, "x": 1, "y": 1 }
				]
			},
			"head": {
				"rotate": [
					{ "time": 0, "angle": -0.13 },
					{ "time": 0.1666, "angle": 0.33 },
					{ "time": 0.3333, "angle": 10.27 },
					{ "time": 0.5, "angle": -6.06 },
					{ "time": 0.6666, "angle": -0.13 }
				],
				"translate": [
					{ "time": 0, "x": 0, "y": 0 },
					{ "time": 0.5, "x": -0.05, "y": 0.29 },
					{ "time": 0.6666, "x": 0, "y": 0 }
				],
				"scale": [
					{ "time": 0, "x": 1, "y": 1, "curve": "stepped" },
					{ "time": 0.6666, "x": 1, "y": 1 }
				]
			}
		}
	}
}
}